hexgrid_cube/__init__.py
hexgrid_cube/grid.py
hexgrid_cube/hex.py
hexgrid_cube/point.py
hexgrid_cube/util.py
hexgrid_cube/vector.py
hexgrid_cube-2.2.2.dist-info/licenses/LICENSE
hexgrid_cube-2.2.2.dist-info/METADATA
hexgrid_cube-2.2.2.dist-info/WHEEL
hexgrid_cube-2.2.2.dist-info/top_level.txt
hexgrid_cube-2.2.2.dist-info/RECORD
