Metadata-Version: 2.4
Name: hexgrid_cube
Version: 2.2.2
Summary: Hex grid utilities using cube coordinates.
Author-email: Quentin Dimarellis <qdimarellis@laposte.net>
License-Expression: CC-BY-4.0
Project-URL: Homepage, https://gitlab.com/loldebyte/hexgrid_cube
Project-URL: Issues, https://gitlab.com/loldebyte/hexgrid_cube/-/issues
Classifier: Programming Language :: Python :: 3
Classifier: Operating System :: OS Independent
Requires-Python: >=3.10
License-File: LICENSE
Dynamic: license-file
